{
  "Name": "Heart rate variability biofeedback training and emotion regulation",
  "BIDSVersion": "1.5.0",
  "DatasetType": "raw",
  "License": "CC0",
  "Authors": [
    "Kaoru Nashiro",
    "Noah Mercer",
    "Hyun Joo Yoo",
    "Jungwon Min",
    "Christine Cho",
    "Shelby L. Bachman",
    "Padideh Nasseri",
    "Shai Porat",
    "Shubir Dutt",
    "Mara Mather"
  ],
  "Acknowledgements": "We thank our research assistants for their help with data collection: Michelle Wong, Kathryn Cassutt, Collin Amano, Yong Zhang, Paul Choi, Heekyung Rachael Kim, Seungyeon Lee, Alexandra Haydinger, Lauren Thompson, Gabriel Shih, Divya Suri, Sophia Ling, Akanksha Jain, and Linette Bagtas.",
  "HowToAcknowledge": "Please cite this paper: Nashiro, K., Min, J., Yoo, H. J., Cho, C., Bachman, S. L., Dutt, S., ... & Mather, M. (2021). Enhancing the brain's emotion regulation capacity with a randomised trial of a 5-week heart rate variability biofeedback intervention. medRxiv.",
  "Funding": [
    "This study was supported by NIH R01AG057184 (PI Mather)"
  ],
  "EthicsApprovals": [
    "Institutional Review Boards (IRBs) UP-17-00219"
  ],
  "ReferencesAndLinks": [
    ""

  ],
  "DatasetDOI": ""
}
